gsamil_test/__init__.py
gsamil_test/py.typed
gsamil_test-0.1.7.dist-info/LICENSE
gsamil_test-0.1.7.dist-info/METADATA
gsamil_test-0.1.7.dist-info/WHEEL
gsamil_test-0.1.7.dist-info/RECORD
