Metadata-Version: 2.1
Name: gsamil-test
Version: 0.1.7
Summary: This is a test python package I created to learn pip&poetry
Home-page: https://github.com/gsamil/sample-pypi
License: MIT
Author: gsamil
Author-email: abdullah-s-guser@hotmail.com
Requires-Python: >=3.8,<4.0
Classifier: Development Status :: 2 - Pre-Alpha
Classifier: Intended Audience :: Developers
Classifier: License :: OSI Approved :: MIT License
Classifier: Natural Language :: English
Classifier: Programming Language :: Python :: 3
Classifier: Programming Language :: Python :: 3.8
Classifier: Programming Language :: Python :: 3.9
Classifier: Programming Language :: Python :: 3.10
Classifier: Programming Language :: Python :: 3.11
Classifier: Programming Language :: Python :: 3.12
Classifier: Programming Language :: Python :: 3.7
Requires-Dist: pytest (==7.2.0)
